[
    {
        "id": 688721,
        "url": "https://homedy.com//ban-nha-rieng-quan-go-vap-tp-ho-chi-minh/lh-phuc-0794062948-can-tien-nen-re-le-loi-50m2-1ty550-shr-hxh-thoang-mat-es3137696",
        "poster": null,
        "price": null,
        "area": null,
        "description": "Cần tiền chữa bệnh nên bán gấp bán rẻ căn nhà ở Lê Lợi phường 4 quận Gò Vấp- DTCN 50m² nở hậu 1m, ngang 4m dài 12,5m, không dính quy hoạch.- Có sổ hồng năm 2017 bao sang tên công chứng.- Bán kính xung quanh 500m có đầy đủ tiện ích như trường học, bệnh viện, ngân hàng, chợ, TTTM.- Trước trước nhà 5m trải nhựa - khu vực điện âm nước máy - hàng xóm thân thiện.- Nằm trong khu an ninh, không trộm cắp.- Thuận lợi mua ở hoặc đầu tư kinh doanh.- Đối diện trường đại học công nghiệp, chợ gò vấp, bệnh viện 175.Miễn cò lái trung gian môi giới.",
        "image_links": "https://img.homedy.com/store/images/2025/05/21/b34-638834369002367327.jpg_200x200.jpg",
        "location_text": "Phường 4, Quận Gò Vấp, TP Hồ Chí Minh",
        "province": "TP Hồ Chí Minh",
        "district": "Quận Gò Vấp",
        "ward": "4",
        "ProvinceID": null,
        "DistrictID": null,
        "WandID": null,
        "HistoryID": null,
        "type": "Nhà riêng",
        "area_text": "50 m2",
        "price_int": null,
        "time_create": "2025-05-26 07:08:55",
        "price_text": "1,55 Tỷ"
    },
    {
        "id": 688723,
        "url": "https://homedy.com//ban-can-ho-quan-binh-thanh-tp-ho-chi-minh/2pn-nguyen-thuong-hien-16ty-full-noi-that-so-hong-rieng-tro-vay-0703-501-089-es3115139",
        "poster": null,
        "price": null,
        "area": null,
        "description": "Khu phức hợp cao cấp đầy đủ tiện ích- Địa Thế Thịnh Vượng Giúp Giá Trị Gia Tăng+ Vị trí dự án nằm ngay đường Nguyễn Thượng Hiền gần sân bay Tân Sơn NhấtGiá 1,65 tỷ 55 m2 có 2 phòng ngủ, 2 toilet bao sang tên- Nội thất căn hộ sử dụng là nội thất cao cấp ngang với tiêu chuẩn của khách sạn 5 sao ( thiết bị smart home…) rất phù hợp cho nhu cầu mua xong ở hoặc kinh doanh cho thuê ..Tiện ích vượt bật: trung tâm thương mại, hồ bơi, trường quốc tế, phòng Gym,..An ninh cao 3 lớp bảo vệ, hệ thống PCCC hiện đại.Giá 1,65 tỷ bao sang tênCho trả góp dài hạn, hỗ trợ vayGọi ngay C. Kim O7O3.5O1.O89 để xem thực tế căn hộ",
        "image_links": "https://img.homedy.com/store/images/2025/02/23/81-638758941713805125.jpg_200x200.jpg",
        "location_text": "Phường 5, Quận Bình Thạnh, TP Hồ Chí Minh",
        "province": "TP Hồ Chí Minh",
        "district": "Quận Bình Thạnh",
        "ward": "5",
        "ProvinceID": null,
        "DistrictID": null,
        "WandID": null,
        "HistoryID": null,
        "type": "Chung cư",
        "area_text": "52 m2",
        "price_int": null,
        "time_create": "2025-05-26 07:08:55",
        "price_text": "1,6 Tỷ"
    },
    {
        "id": 688724,
        "url": "https://homedy.com//ban-can-ho-quan-go-vap-tp-ho-chi-minh/moi-co-so-san-pham-van-dong-2pn-view-boi-158-ty-55m2-full-noi-that-o7o3-5o1-o89-es3137690",
        "poster": null,
        "price": null,
        "area": null,
        "description": "- Thiết kế theo phong cách hiện đại, tận dụng tối đa ngõ ngách căn phòng, không gian rộng rãi thoáng mát.- 2 phòng ngủ, 2 toilet, phòng khách, bếp, ban công rộng đón gió cực mát.- Tầng trệt: Có trung tâm dịch vụ, vui chơi mua sắm, gym, hồ bơi vô cực.- Ngay trung tâm giáp bên sân bay, Phú Nhuận, Bình Thạnh, đi Quận 1 có 7 phút- Sân thượng: Cafe sân thượng, hồ tiểu cảnh, khu nướng BBQ ngắm toàn cảnh TPHCM.- Tầng hầm cực rộng, 4 thang máy, 4 thang bộ, hệ thông báo khói, báo cháy cao cấp cảm biến.Giá 1,58 tỷ, diện tích 55 m².- Hỗ trợ vay ngân hàng dài hạnSổ hồng riêng bao hết tất cả chi phí sang tên.- Nội thất cao cấp có sẵn mới: Bộ Sofa, bàn ăn, bếp, nệm, tivi, tủ lạnh, máy lạnh, máy giặt.- Nhận nhà vào ở như hình.- Không ở căn này cho thuê được 14 triệu/ tháng lại nếu khách mua không ở.- Khu an ninh 24/7, khu căn hộ văn minh, yên tĩnh.Gọi chính chủ C.Kim O7O3.5O1.O89 xem căn hộ",
        "image_links": "https://img.homedy.com/store/images/2025/05/21/371-638834362361346401.jpg_200x200.jpg",
        "location_text": "Phường 3, Quận Gò Vấp, TP Hồ Chí Minh",
        "province": "TP Hồ Chí Minh",
        "district": "Quận Gò Vấp",
        "ward": "3",
        "ProvinceID": null,
        "DistrictID": null,
        "WandID": null,
        "HistoryID": null,
        "type": "Chung cư",
        "area_text": "55 m2",
        "price_int": null,
        "time_create": "2025-05-26 07:08:55",
        "price_text": "1,58 Tỷ"
    },
    {
        "id": 688725,
        "url": "https://homedy.com//ban-dat-nen-du-an-khu-dan-cu-13a-hong-quang/chinh-chu-can-gap-lo-nha-pho-6x18-a2-gan-ta-buu-gia-3-ty-460-es3133942",
        "poster": null,
        "price": null,
        "area": null,
        "description": "Cần bán nền đất A2 nhà phố 6x18 ngay sát bên đường Tạ Quang Bửu thuộc KDC 13A Hồng Quang.Vị trị đẹp đối diện trường ĐH Kinh Tế TP.HCM đường trước nhà 21m.Giá 3 Tỷ 460 (bao sang tên) . Pháp lý hợp đồng góp vốn .Liên hệ mua đất : A.Huy -0909 342***",
        "image_links": "https://img.homedy.com/store/images/2025/05/07/z6504128271093-d3a8516f8872b480740369df6b926339-638822243915437644.jpg_200x200.jpg",
        "location_text": "Xã Phong Phú, Huyện Bình Chánh, TP Hồ Chí Minh",
        "province": "TP Hồ Chí Minh",
        "district": "Huyện Bình Chánh",
        "ward": "Phong Phú",
        "ProvinceID": null,
        "DistrictID": null,
        "WandID": null,
        "HistoryID": null,
        "type": "Đất đấu giá/Đất thổ cư",
        "area_text": "108 m2",
        "price_int": null,
        "time_create": "2025-05-26 07:08:55",
        "price_text": "3,46 Tỷ"
    },
    {
        "id": 688726,
        "url": "https://homedy.com//ban-dat-nen-du-an-13b-conic-phong-phu/chinh-chu-can-dep-an13b-gia-chi-7-ty-9-duong-di-vao-co-so-do-view-es3133288",
        "poster": null,
        "price": null,
        "area": null,
        "description": "CHÍNH CHỦ BÁN GẤP NỀN ĐẸP DỰ ÁN 13B CONIC – GIÁ CHỐT NHANH – VIEW CỰC PHẨM 💎🏡🎯 Giá chỉ: 7,9 TỶ – Diện tích: 126m² (7x18m) – SỔ HỒNG RIÊNG, CẦM TAY📢 Cơ hội đầu tư – An cư lý tưởng giữa trung tâm Quận Bình Chánh (sát Quận 8, Quận 5)Vì cần tiền gấp cho con đi du học, tôi bán nhanh lô đất vàng tại khu đô thị 13B Conic – Vị trí không thể đẹp hơn!📍 Toạ lạc cực đắc địa:Đối diện ĐH Văn Hiến - Kề bên ĐH Kinh Tế TP.HCM - Khu dân cư hiện hữu, an ninh, trí thức, dân trí cao💥 Tiện ích nội khu đầy đủ, sống chuẩn resort mỗi ngày:🏢 Chung cư hiện hữu – 🛒 Siêu thị – 🏋️ Phòng gym – 🎾 Sân tennis – 🏊 Hồ bơi – 🌳 Công viên cây xanh thoáng mát🚗 Hạ tầng hoàn chỉnh – Đường trước nhà 14m rộng rãi – Ô tô tránh nhau thoải mái🧭 Hướng Tây Nam – View đẹp, thoáng, đón gió mát cả ngày📈 Tiềm năng tăng giá mạnh – Khu vực đang phát triển sôi động, dân cư về ở ngày càng đông💸 Ngân hàng hỗ trợ vay lên đến 70% – Pháp lý chuẩn chỉnh – Công chứng sang tên ngay👉 Giá bán chỉ: 7,9 TỶ – GỌI NGAY: Anh Huy –0909 342***",
        "image_links": "https://img.homedy.com/store/images/2025/05/05/z6504125293630-45c1b3f0e1e4e17ebd205ff987721d45-638820399373342825.jpg_200x200.jpg",
        "location_text": "Xã Phong Phú, Huyện Bình Chánh, TP Hồ Chí Minh",
        "province": "TP Hồ Chí Minh",
        "district": "Huyện Bình Chánh",
        "ward": "Phong Phú",
        "ProvinceID": null,
        "DistrictID": null,
        "WandID": null,
        "HistoryID": null,
        "type": "Chung cư",
        "area_text": "126 m2",
        "price_int": null,
        "time_create": "2025-05-26 07:08:55",
        "price_text": "7,9 Tỷ"
    },
    {
        "id": 688727,
        "url": "https://homedy.com//ban-dat-nen-du-an-khu-dan-cu-green-life-13c/ket-von-kinh-doanh-can-gap-lo-j-nha-pho-5x17-so-do-greenlife-gia-5-2ty-es3128757",
        "poster": null,
        "price": null,
        "area": null,
        "description": "Kẹt vốn Kinh Doanh cần bán gấp lô J đất nền nhà phố 5x17 ( sổ đỏ ) KDC 13C Greenlife đối diện trường đại học Văn Hiến HCM , cạnh bên trường cấp quốc tế AES 200m , có đầy đủ tiện ích Hồ Bơi, sân Tennis , khu dân cư đông đúc , an ninh bao vể 24/24 . Vị trí hướng Tây Bắc đã có sổ đỏ Ngân Hàng hỗ trợ vay đến 70% .Giá bán : 5,2 Tỷ . Liên hệ Huy0909342***",
        "image_links": "https://img.homedy.com/store/images/2025/04/16/z6509583240900-e1fa2f1cd14ccbded02a4b4c554768c4-638803916107168130.jpg_200x200.jpg",
        "location_text": "Xã Phong Phú, Huyện Bình Chánh, TP Hồ Chí Minh",
        "province": "TP Hồ Chí Minh",
        "district": "Huyện Bình Chánh",
        "ward": "Phong Phú",
        "ProvinceID": null,
        "DistrictID": null,
        "WandID": null,
        "HistoryID": null,
        "type": "Đất đấu giá/Đất thổ cư",
        "area_text": "85 m2",
        "price_int": null,
        "time_create": "2025-05-26 07:08:55",
        "price_text": "5,2 Tỷ"
    },
    {
        "id": 688659,
        "url": "https://homedy.com//ban-nha-mat-pho-quan-ha-dong-ha-noi/tien-p-nguyen-trai-lh-0972078667-es3126677",
        "poster": null,
        "price": null,
        "area": null,
        "description": null,
        "image_links": "https://img.homedy.com/store/images/2025/04/08/ban-nha-mat-tien-mat-pho-ha-dong-0972-078-667-1-638797074828166672.jpg_200x200.jpg",
        "location_text": "Đường Quang Trung, Quang Trung",
        "province": null,
        "district": null,
        "ward": null,
        "ProvinceID": null,
        "DistrictID": null,
        "WandID": null,
        "HistoryID": null,
        "type": null,
        "area_text": "50 m2",
        "price_int": null,
        "time_create": "2025-05-26 07:08:54",
        "price_text": "10,95 Tỷ"
    },
    {
        "id": 688661,
        "url": "https://homedy.com//ban-nha-rieng-quan-thanh-xuan-ha-noi/phuong-liet-o-to-do-cua-san-de-xe-gia-chi-13-x-ty-es3134682",
        "poster": null,
        "price": null,
        "area": null,
        "description": "PHÂN LÔ KHU CÁN BỘ - Ô TÔ ĐỖ CỬA - NHÀ CÓ 2 MẶT NGÕ THOÁNG TRƯỚC SAU - DIỆN TÍCH RỘNG VỊ TRÍ ĐẸP Ở CỰC SƯỚNG.Tầng 1: Sân cổng, Để xe + P.Khách + Bếp.Tầng 2 +3+4 : 3 PN master.Tầng 5: P.Thờ + sân phơi.",
        "image_links": "https://img.homedy.com/store/images/2025/05/10/0cb4e495-1393-42ac-84ac-86c760e02389-638824603361346756.jpg_200x200.jpg",
        "location_text": "Quận Thanh Xuân,  Hà Nội",
        "province": null,
        "district": null,
        "ward": null,
        "ProvinceID": null,
        "DistrictID": null,
        "WandID": null,
        "HistoryID": null,
        "type": "Nhà riêng",
        "area_text": "55 m2",
        "price_int": null,
        "time_create": "2025-05-26 07:08:54",
        "price_text": "13,5 Tỷ"
    },
    {
        "id": 688662,
        "url": "https://homedy.com//ban-nha-rieng-quan-long-bien-ha-noi/456m2-4-tang-no-hau-gara-o-to-khu-918-phuc-dong-an-cu-lien-ke-san-golf-es3137857",
        "poster": null,
        "price": null,
        "area": null,
        "description": "Chính chủ bán 45,6m2 nhà 4 tầng nở hậu, gara ô tô, Khu 918 Phúc Đồng - An cư liền kề Sân Golf Long Biên.+ Diện tích: 45,6m2, mặt tiền 3,7m, nở hậu 3,75m,tọa hướng Đông Bắc.+ Giá bán:12.3 tỷ đồng ( có ra lộc cho người mua ).+ Hiện trạng có có nhà 4 tầng, cầu thang ở giữa, mỗi tầng chia đôi 2 phòng, tầng 1 gara ô tô, xe máy, tầng 2 phòng khách và phòng ăn, tầng 3 hai phòng ngủ, tầng 4 phòng thờ và sân phơi. Khu vực dân trí cao, xung quanh bạt ngàn tiện ích, vị trí đi lại cực kỳ thuận tiện, gần đường QL5A, gần cầu Vĩnh Tuy. Hãy nhanh tay sở hữu ngôi nhà trên...+ Pháp lý: Sổ đỏ chính chủ, không thế chấp, sẵn sàng công chứng.+ Hỗ trợ: Cam kết bán đúng giá, không thu phí người mua, check quy hoạch, vay bank, thủ tục sang tên.Tất cả vì khách hàng:0925333***-0934498***Kinh doanh sản phẩm đầu tư chúng ta cần kiến thức, kinh nghiệm và trải nghiệm!",
        "image_links": "https://img.homedy.com/store/images/2025/05/22/z6054057211914-4f44ceffb046c27f0a4f5b2362480867-638834953109789269.jpg_200x200.jpg",
        "location_text": "Quận Long Biên,  Hà Nội",
        "province": null,
        "district": null,
        "ward": null,
        "ProvinceID": null,
        "DistrictID": null,
        "WandID": null,
        "HistoryID": null,
        "type": "nha-mat-pho",
        "area_text": "45,6 m2",
        "price_int": null,
        "time_create": "2025-05-26 07:08:54",
        "price_text": "12,3 Tỷ"
    },
    {
        "id": 688664,
        "url": "https://homedy.com//ban-nha-rieng-quan-cau-giay-ha-noi/yen-hoa-5-tang-dep-nhu-mo-so-vuong-gia-chi-795-ty-es3137850",
        "poster": null,
        "price": null,
        "area": null,
        "description": "Nhà đẹp từng chi tiết – thiết kế 5 tầng hiện đại, nội thất nhập khẩu tinh tếMỗi tầng là 1 phòng Master riêng biệt, rộng rãi – rất hợp với gia đình 3 thế hệTầng 5 có sân BBQ tổ chức tiệc chill cực đỉnhCách ô tô 20m –, Bộ NN,UBND,  tiện ích xung quanh không thiếu thứ gì!Sổ đỏ hoa khôi – chủ thiện chí bán – giá chỉ 7.95 tỷLiên hệ : Ms Uyên –0968454***Chuyên hỗ trợ, mua và bán Nhà đất khu vực Cầu giấy trong phân khúc 7-15 tỷ (Miễn TG)",
        "image_links": "https://img.homedy.com/store/images/2025/05/22/1-638834909844516367.jpg_200x200.jpg",
        "location_text": "Quận Cầu Giấy,  Hà Nội",
        "province": null,
        "district": null,
        "ward": null,
        "ProvinceID": null,
        "DistrictID": null,
        "WandID": null,
        "HistoryID": null,
        "type": "Đất đấu giá/Đất thổ cư",
        "area_text": "30 m2",
        "price_int": null,
        "time_create": "2025-05-26 07:08:54",
        "price_text": "7,95 Tỷ"
    },
    {
        "id": 688665,
        "url": "https://homedy.com//ban-nha-rieng-quan-10-tp-ho-chi-minh/gap-can-5-tang-lhp-q10thong-tu-phuongno-hau-8tydt-san-119m2-so-hong-phap-ly-day-du-es2940618",
        "poster": null,
        "price": null,
        "area": null,
        "description": "Gấp! Nhà 5 tấng LHP Q10,thông tứ phương,nở hậu 7tỷ9+ Pháp lý: GPXD, hồ sơ hoàn công đầy đủ, Sổ hồng năm 2022+ Kết cấu: Nhà 1 Trệt, 3 lầu, sân thượng . Gồm 3PN, 5WC, PK, bếp, ban công thoáng mát. Thiết kế hiện đại, sang trọng vào ở ngay.+ Diện tích: 33m2 (3m1x11m); Diện tích sử dụng 120m2Nhà đang có hợp đồng thuê CHDV thu nhập 17tr, cần tiền trả về cho ngân hàng nên Bán căn nhà tự tay chăm chút lâu nay. Tài lộc để lại cho khách kết duyên.+ Vị trí đắc địa khu trung tâm Quận 10, đảm bảo khu vực này rất an ninh, lịch sự, không bị ngập nước cho dù mưa lớn, giao thông thì ko cần bàn rồi rất thuận tiện đi lại giữa các quận, Bệnh viện ,trường học ,chợ ,nhà thờ , siêu thị cửa hàng tiện ích gần sát nhà ...nay do không trả lãi ngân hàng nổi nên cần bán gấp vì vậy mình để lại giá nhà khá tốt và còn thương lượng cho khách thiện chíACE môi giới bán giúp mình gởi hoa hồng nhé!",
        "image_links": "https://img.homedy.com/store/images/2024/06/25/z5572673854354-e9f5754f0e14e9232969e380cf919e1b-638549330899705872.jpg_200x200.jpg",
        "location_text": "Phường 1, Quận 10, TP Hồ Chí Minh",
        "province": "TP Hồ Chí Minh",
        "district": "Quận 10",
        "ward": "1",
        "ProvinceID": null,
        "DistrictID": null,
        "WandID": null,
        "HistoryID": null,
        "type": "Nhà riêng",
        "area_text": "33 m2",
        "price_int": null,
        "time_create": "2025-05-26 07:08:54",
        "price_text": "7,9 Tỷ"
    },
    {
        "id": 688667,
        "url": "https://homedy.com//ban-nha-rieng-quan-7-tp-ho-chi-minh/44m2-4pn-4-tang-gia-5-3-ty-hem-pham-huu-lau-es3137839",
        "poster": null,
        "price": null,
        "area": null,
        "description": "Bán nhà hẻm Phạm Hữu Lầu 43m² - 4PN - 3WC - Giá 5.3 tỷ - Quận 7.- Diện tích: 4.2 x 10.4 (44m²).- Nội thất: Cơ bản.- Kết cấu: Trệt, 2 lầu, sân thượng, 4PN, 3WC.- Khu dân cư hiện hữu, dân trí cao, an ninh tốt.- Pháp lý chuẩn - Sổ hồng riêng - Hoàn công đủ - Công chứng ngay.- Gần khu Phú Mỹ Hưng, khu phố Nam Viên.- Gần khu tái định cư Phú Mỹ.- Gần Crescent Mall. Gần trung tâm hội chợ và triển lãm Sài Gòn.- Gần kho xăng dầu Nhà Bè.- Gần chợ Phước Long, Chợ Phú Xuân, Chợ Dân Sinh Nhà Bè.- Gần Coopmart Huỳnh Tấn Phát.- Gần sông Soài Rạp.- Gần khu phức hợp Sài Gòn PeninSula Quận 7.- Gần cầu Phú Mỹ, cầu Cả Cấm 2, cầu Phước Long, cầu Phú Thuận, cầu Phú Xuân 2, cầu Ánh Sao.- Gần Trung tâm văn hoá Q7, Ban chỉ huy quân sự, Trung tâm hành chính, Cảnh sát quân đội, Uỷ ban nhân dân, Viên kiểm soát nhân dân.- Gần trường tiểu học Phú Mỹ, trường trung học cơ sở Hoàng Quốc Việt, trường Quốc tế Canada - Việt Nam, trường tiểu học Phạm Hữu Lầu, trường trung học cơ sở Phạm Hữu Lầu, trường trung học cơ sở Ngô Quyền, trường quốc tế Hàn Quốc, trường quốc tế Đài Loan, trường quốc tế Nhật Bản, trường TH - THCS - THPT Nam Sài Gòn, trường tiểu học Phú Thuận.- Gần trường Cao Đẳng Giao Thông Vận Tải Đường thủy II.- Gần bệnh viện Tâm Đức, Trung tâm y tế Q7, Trung tâm y tế Nhà Bè, phòng khám tư nhân.- Gần đường Huỳnh Tấn Phát, Phạm Hữu Lầu, Hoàng Quốc Việt, Đào Trí, Lê Văn Lương, Nguyễn Hữu Thọ, Phú Thuận, Nguyễn Văn Linh, Lê Thị Chợ, Gò Ô Môi, Tân Phú, Nguyễn Văn Tưởng.",
        "image_links": "https://img.homedy.com/store/images/2025/05/22/debfa668-f0ba-4bea-9692-b94e5fed10e3-638834690783671561.jpg_200x200.jpg",
        "location_text": "Phường Phú Mỹ, Quận 7, TP Hồ Chí Minh",
        "province": "TP Hồ Chí Minh",
        "district": "Quận 7",
        "ward": "Phú Mỹ",
        "ProvinceID": null,
        "DistrictID": null,
        "WandID": null,
        "HistoryID": null,
        "type": "Nhà riêng",
        "area_text": "44 m2",
        "price_int": null,
        "time_create": "2025-05-26 07:08:54",
        "price_text": "5,3 Tỷ"
    },
    {
        "id": 688669,
        "url": "https://homedy.com//ban-nha-rieng-quan-phu-nhuan-tp-ho-chi-minh/khu-sam-uat-le-van-sy-moi-full-noi-that-3-lau-4pn-es3137821",
        "poster": null,
        "price": null,
        "area": null,
        "description": null,
        "image_links": "https://img.homedy.com/store/images/2025/05/21/z6621740742966-0a95f50ee4b1d46d18d9d14c4632f0df-638834651669497189.jpg_200x200.jpg",
        "location_text": "Quận Phú Nhuận,  TP Hồ Chí Minh",
        "province": null,
        "district": null,
        "ward": null,
        "ProvinceID": null,
        "DistrictID": null,
        "WandID": null,
        "HistoryID": null,
        "type": null,
        "area_text": "46 m2",
        "price_int": null,
        "time_create": "2025-05-26 07:08:54",
        "price_text": "7 Tỷ"
    },
    {
        "id": 688670,
        "url": "https://homedy.com//ban-nha-mat-pho-quan-tan-phu-tp-ho-chi-minh/khach-san-khu-thang-may-dang-co-24-pn-noi-that-dau-tu-kinh-doanh-lau-dai-es3137817",
        "poster": null,
        "price": null,
        "area": null,
        "description": "KHUÔNG VIỆT, P. PHÚ TRUNG, Q. TÂN PHÚMẶT TIỀN TÂN PHÚ - KHÁCH SẠN NGAY CÔNG VIÊN NƯỚC ĐẦM SEN – DOANH THU KHỦNGDiện tích: 96m2 (4x 24).Kết cấu: Kết 1 trệt, 6 lầu, sân thượng, có thang máy.Có 24 phòng, trong đó có 10 phòng đôi, 25 WC. Đã từng có hợp đồng thuê khoán 6 năm: 80 triệu/ tháng. Chủ tự khai thác dòng tiền lên đến 200 triệu.Vị trí: Mặt tiền kinh doanh khai thác dòng tiền tốt, ngay CV Đầm Sen.Tiện ích: Ngay CV Văn Hóa Đầm Sen, sân vận động Đầm Sen, Trung tâm TDTT, và nhiều tiện ích khác....Pháp lý: chuẩn, công chứng ngay.Giá chỉ 20.x TỶLiên hệ để được xem nhà miễn phí :09353254***Mr.Phương hoặc Ms.Tâm0968415***",
        "image_links": "https://img.homedy.com/store/images/2025/05/21/z6621736447720-7d606b9069cd7d734bd12541f4edb0f2-638834648902212973.jpg_200x200.jpg",
        "location_text": "Phường Phú Trung, Quận Tân Phú, TP Hồ Chí Minh",
        "province": "TP Hồ Chí Minh",
        "district": "Quận Tân Phú",
        "ward": "Phú Trung",
        "ProvinceID": null,
        "DistrictID": null,
        "WandID": null,
        "HistoryID": null,
        "type": "nha-mat-pho",
        "area_text": "96 m2",
        "price_int": null,
        "time_create": "2025-05-26 07:08:54",
        "price_text": "20 Tỷ"
    },
    {
        "id": 688671,
        "url": "https://homedy.com//ban-nha-rieng-quan-tan-phu-tp-ho-chi-minh/gia-re-1-tret-lung-khu-hxh-quay-dau-es3137815",
        "poster": null,
        "price": null,
        "area": null,
        "description": "NGUYỄN QUÝ ANH, P. TÂN SƠN NHÌ, QUẬN TÂN PHÚNhà HXH – P. TÂN SƠN NHÌ – TÂN PHÚ – 46M2Diện tích: 46m2 (3.4x 13.65).Kết cấu: Kết cấu 1 trệt, 1 lừng nhà cũ.Vị trí: Hẻm xe hơi quay đầu.Tiện ích: Ngay trường CĐ Công Thương, Các trường C1, 2, 3, khu ăn uống giải trí sầm uất....Pháp lý: chuẩn, công chứng ngay.Giá chỉ 4 tỷ x nhỏ xíuLiên hệ để được xem nhà miễn phí :09353254***Mr.Phương hoặc Ms.Tâm0968415***",
        "image_links": "https://img.homedy.com/store/images/2025/05/21/z6621732305538-d7cc649408130104884c0ed33c06978b-638834643985793637.jpg_200x200.jpg",
        "location_text": "Phường Tân Sơn Nhì, Quận Tân Phú, TP Hồ Chí Minh",
        "province": "TP Hồ Chí Minh",
        "district": "Quận Tân Phú",
        "ward": "Tân Sơn Nhì",
        "ProvinceID": null,
        "DistrictID": null,
        "WandID": null,
        "HistoryID": null,
        "type": "Nhà riêng",
        "area_text": "46 m2",
        "price_int": null,
        "time_create": "2025-05-26 07:08:54",
        "price_text": "4 - 4,5 Tỷ"
    },
    {
        "id": 688672,
        "url": "https://homedy.com//ban-nha-mat-pho-thi-xa-phu-my-ba-ria-vung-tau/chinh-chu-can-nhanh-tien-duong-pham-van-dong-tt-tan-thanh-es3137808",
        "poster": null,
        "price": null,
        "area": null,
        "description": "CHÍNH CHỦ Cần Bán Nhanh Nhà Mặt Tiền Đường Phạm Văn Đồng, TT Phú Mỹ, Tân Thành, Bà Rịa Vũng Tàu* Diện tích: 445m2 (120m2 thổ cư)- Giá bán : 22 tỷ (có thương lượng )- Vị Trí : nhà mặt tiền Phạm Văn Đồng, nhà trệt, kết cấu gồm 2PN, 1WC- Tiện ích xung quanh đầy đủ: gần trường , chợ , ủy ban nhân dân,...- Khu dân cư đông đúc, an ninh, thân thiện.- Giao thông thuận tiện, di chuyển dễ dàng.- Phù hợp: Định cư lâu dài, Kinh Doanh mọi ngành nghề, cho thuê, sinh lời.- Pháp lý: Sổ hồng chính chủ, sang tên nhanh chóng.Liên hệ ngay chị Phượng0901338***",
        "image_links": "https://img.homedy.com/store/images/2025/05/21/z6596777840937-2bcff2e0a65c813a0292a68924c52523-638834609514122836.jpg_200x200.jpg",
        "location_text": "Phường Phú Mỹ, Thị xã Phú Mỹ, Bà Rịa Vũng Tàu",
        "province": "Bà Rịa Vũng Tàu",
        "district": "Thị xã Phú Mỹ",
        "ward": "Phú Mỹ",
        "ProvinceID": null,
        "DistrictID": null,
        "WandID": null,
        "HistoryID": null,
        "type": "nha-mat-pho",
        "area_text": "445 m2",
        "price_int": null,
        "time_create": "2025-05-26 07:08:54",
        "price_text": "22 Tỷ"
    },
    {
        "id": 688675,
        "url": "https://homedy.com//ban-can-ho-quan-ha-dong-ha-noi/trong-phong-o-ngay-chan-toa-mipec-kien-hung-duoc-luon-gio-giac-tuu-do-1-coc-es3137795",
        "poster": null,
        "price": null,
        "area": null,
        "description": "giá 4trđiện : 3,75k/ sốnước 32k khốiwifi 100k 1 phòngdvc : 70k ngườiLiên hệ :0384 250***",
        "image_links": "https://img.homedy.com/store/images/2025/05/21/z6591851019223-986e0a41ebd3565a8ea9a7d90cc24e95-638834585627410952.jpg_200x200.jpg",
        "location_text": "Quận Hà Đông,  Hà Nội",
        "province": null,
        "district": null,
        "ward": null,
        "ProvinceID": null,
        "DistrictID": null,
        "WandID": null,
        "HistoryID": null,
        "type": null,
        "area_text": "25 m2",
        "price_int": null,
        "time_create": "2025-05-26 07:08:54",
        "price_text": "4,2 Triệu"
    },
    {
        "id": 688676,
        "url": "https://homedy.com//ban-can-ho-quan-dong-da-ha-noi/gap-2-rong-115m-gia-re-nhat-pho-thai-thinh-es3137787",
        "poster": null,
        "price": null,
        "area": null,
        "description": "2 căn hộ riêng biệt tại tòa A và tòa B – mặt phố Thái Thịnh, trung tâm quận Đống ĐaDiện tích: 115m² – 2PN, 2WC, phòng khách cực rộng, bếp riêng biệtCăn góc, thoáng sáng tự nhiên quanh năm, ban công view đẹpCó thể cải tạo thành 3-4PN nếu cầnTọa lạc tại 2 tòa A & B, vị trí trung tâm quận Đống ĐaGiá bán MỀM NHẤT khu vực – rẻ hơn mọi căn cùng phân khúc!",
        "image_links": "https://img.homedy.com/store/images/2025/05/21/z6624597873686-554a656409b24342e352cd7139f83243-638834524249214869.jpg_200x200.jpg",
        "location_text": "Phường Ngã Tư Sở, Quận Đống Đa, Hà Nội",
        "province": "Hà Nội",
        "district": "Quận Đống Đa",
        "ward": "Ngã Tư Sở",
        "ProvinceID": 24,
        "DistrictID": 6,
        "WandID": null,
        "HistoryID": null,
        "type": "Chung cư",
        "area_text": "115 m2",
        "price_int": null,
        "time_create": "2025-05-26 07:08:54",
        "price_text": "8 Tỷ"
    },
    {
        "id": 688677,
        "url": "https://homedy.com//ban-nha-rieng-quan-go-vap-tp-ho-chi-minh/sieu-pham-5-tang-o-to-vao-tan-hem-rong-gan-lang-hoa-gia-nhinh-8-ty-es3137782",
        "poster": null,
        "price": null,
        "area": null,
        "description": "✔️ Nhà mới đẹp, thiết kế hiện đại:1 trệt, 1 lửng, 3 lầu✔️5 phòng ngủ, 4 toilet, không gian rộng rãi, đầy đủ tiện nghi✔️ Hẻm rộng –xe tải đậu tận cửa,xe hơi ngủ trong nhàthoải mái✔️Vị trí vàngtrung tâm Gò Vấp – gần công viên Làng Hoa, thuận tiện di chuyển ra các trục đường lớn✔️ Khu dân trí cao, an ninh đảm bảo, hàng xóm thân thiện📝Phù hợp để ở, mở văn phòng, kinh doanh online hoặc cho thuêLiên hệ Thành Danh xem nhà trực tiếp :0365252576***0343939***",
        "image_links": "https://img.homedy.com/store/images/2025/05/21/38037-638834499025163933.jpg_200x200.jpg",
        "location_text": "Phường 8, Quận Gò Vấp, TP Hồ Chí Minh",
        "province": "TP Hồ Chí Minh",
        "district": "Quận Gò Vấp",
        "ward": "8",
        "ProvinceID": null,
        "DistrictID": null,
        "WandID": null,
        "HistoryID": null,
        "type": "Nhà riêng",
        "area_text": "43 m2",
        "price_int": null,
        "time_create": "2025-05-26 07:08:54",
        "price_text": "8 Tỷ"
    },
    {
        "id": 688678,
        "url": "https://homedy.com//ban-dat-huyen-chau-duc-ba-ria-vung-tau/ngop-dep-gia-re-15x90-80m2-tho-cu-bau-chinh-es3137778",
        "poster": null,
        "price": null,
        "area": null,
        "description": "ngộp chủ hạ giá bán gấp lô đất thổ cư tại bàu chinh châu đức, ngay sát trụ đường kim long láng lớn , 15m mặt đường nhựa 8m. sâu 90m vuông vức , đất ở, có 80m2 thổ cưđất đỏ bằng phẳng, khu vực dân cưgiá bán nhanh 1.85 tỉ",
        "image_links": "https://img.homedy.com/store/images/2025/05/21/z6624517141291-a7d80fe0c180f9e8dd6d91dd45fa55bc-638834462701684590.jpg_200x200.jpg",
        "location_text": "Xã Bàu Chinh, Huyện Châu Đức, Bà Rịa Vũng Tàu",
        "province": "Bà Rịa Vũng Tàu",
        "district": "Huyện Châu Đức",
        "ward": "Bàu Chinh",
        "ProvinceID": null,
        "DistrictID": null,
        "WandID": null,
        "HistoryID": null,
        "type": "Đất đấu giá/Đất thổ cư",
        "area_text": "1341 m2",
        "price_int": null,
        "time_create": "2025-05-26 07:08:54",
        "price_text": "1,85 Tỷ"
    }
]